[
  {
    "item": [
      {
        "id": "dd085cc3-0bf6-412e-ada7-eb34aeea318d",
        "image": "bali.jpg",
        "title": "Fly to Bali, Indonesia for only $918",
        "promotion": "Last minute ticket with 15%",
        "bron": "Book now",
        "lan": "EN"
      },
      {
        "id": "56dd0ddd-d363-4a8b-8b22-b6c583010a00",
        "image": "bali.jpg",
        "title": "Летите на Бали, Индонезия всего за 918 долларов.",
        "promotion": "Горящий билет со скидкой 15%",
        "bron": "Забронируйте сейчас",
        "lan": "RU"
      },
      {
        "id": "7b197f64-60a7-47b3-a891-c108b76c6a70",
        "image": "bali.jpg",
        "title": "Болгону 918 долларга Индонезиянын Бали шаарына учуңуз",
        "promotion": "15% менен акыркы мүнөттүк билет",
        "bron": "Азыр ээлеңиз",
        "lan": "KY"
      },
      {
        "id": "c0e4d8bf-13ae-4ca2-b534-0739a1af5f3c",
        "image": "bali.jpg",
        "title": "Sadece 918 $ karşılığında Bali, Endonezya'ya uçun",
        "promotion": "%15 indirimli son dakika bileti",
        "bron": "Şimdi rezervasyon yapın",
        "lan": "TR"
      }
    ]
  },
  {
    "item": [
      {
        "id": "dd085cc3-0bf6-412e-ada7-eb34aeea318d",
        "image": "bankgok.jpg",
        "title": "Direct flights to Bangkok,\nThailand for only $755",
        "promotion": "Last minute ticket with 15%",
        "bron": "Book now",
        "lan": "EN"
      },
      {
        "id": "56dd0ddd-d363-4a8b-8b22-b6c583010a00",
        "image": "bankgok.jpg",
        "title": "Прямые рейсы в Бангкок, Тайланд всего за 755 $",
        "promotion": "Горящий билет со скидкой 25%",
        "bron": "Забронируйте сейчас",
        "lan": "RU"
      },
      {
        "id": "7b197f64-60a7-47b3-a891-c108b76c6a70",
        "image": "bankgok.jpg",
        "title": "Бангкокко түз каттамдар, Таиланд болгону 755 $",
        "promotion": "25% менен акыркы мүнөттүк билет",
        "bron": "Азыр ээлеңиз",
        "lan": "KY"
      },
      {
        "id": "c0e4d8bf-13ae-4ca2-b534-0739a1af5f3c",
        "image": "bankgok.jpg",
        "title": "Sadece 755 $ karşılığında Bangkok, Tayland'a direkt uçuşlar",
        "promotion": "%25 indirimli son dakika bileti",
        "bron": "Şimdi rezervasyon yapın",
        "lan": "TR"
      }
    ]
  },
  {
    "item": [
      {
        "id": "dd085cc3-0bf6-412e-ada7-eb34aeea318d",
        "image": "phuket.jpg",
        "title": "Fly to Bali, Indonesia for only $918",
        "promotion": "Last minute ticket with 25%",
        "bron": "Book now",
        "lan": "EN"
      },
      {
        "id": "56dd0ddd-d363-4a8b-8b22-b6c583010a00",
        "image": "phuket.jpg",
        "title": "Пхукет, Природа Пхукета $811",
        "promotion": "Горящий билет со скидкой 25%",
        "bron": "Забронируйте сейчас",
        "lan": "RU"
      },
      {
        "id": "7b197f64-60a7-47b3-a891-c108b76c6a70",
        "image": "phuket.jpg",
        "title": "Пхукет, Табият Пхукет $811",
        "promotion": "25% менен акыркы мүнөттүк билет",
        "bron": "Азыр ээлеңиз",
        "lan": "KY"
      },
      {
        "id": "c0e4d8bf-13ae-4ca2-b534-0739a1af5f3c",
        "image": "phuket.jpg",
        "title": "Phuket, Doğa Phuket $811",
        "promotion": "%25 indirimli son dakika bileti",
        "bron": "Şimdi rezervasyon yapın",
        "lan": "TR"
      }
    ]
  }
]